snakemake_executor_plugin_htcondor/__init__.py
snakemake_executor_plugin_htcondor-0.1.2.dist-info/LICENSE
snakemake_executor_plugin_htcondor-0.1.2.dist-info/METADATA
snakemake_executor_plugin_htcondor-0.1.2.dist-info/WHEEL
snakemake_executor_plugin_htcondor-0.1.2.dist-info/RECORD
